odoo/addons/iot_rule/README.rst
odoo/addons/iot_rule/__init__.py
odoo/addons/iot_rule/__manifest__.py
odoo/addons/iot_rule/demo/iot_key_demo.xml
odoo/addons/iot_rule/demo/iot_lock_demo.xml
odoo/addons/iot_rule/demo/iot_rule_demo.xml
odoo/addons/iot_rule/i18n/es.po
odoo/addons/iot_rule/i18n/iot_rule.pot
odoo/addons/iot_rule/i18n/it.po
odoo/addons/iot_rule/models/__init__.py
odoo/addons/iot_rule/models/iot_device.py
odoo/addons/iot_rule/models/iot_device_input.py
odoo/addons/iot_rule/models/iot_key.py
odoo/addons/iot_rule/models/iot_key_action.py
odoo/addons/iot_rule/models/iot_lock.py
odoo/addons/iot_rule/models/iot_rule.py
odoo/addons/iot_rule/models/res_partner.py
odoo/addons/iot_rule/readme/CONTRIBUTORS.md
odoo/addons/iot_rule/readme/DESCRIPTION.md
odoo/addons/iot_rule/security/ir.model.access.csv
odoo/addons/iot_rule/static/description/icon.png
odoo/addons/iot_rule/static/description/icon.svg
odoo/addons/iot_rule/static/description/index.html
odoo/addons/iot_rule/tests/__init__.py
odoo/addons/iot_rule/tests/test_iot_rule.py
odoo/addons/iot_rule/views/iot_device_input.xml
odoo/addons/iot_rule/views/iot_key.xml
odoo/addons/iot_rule/views/iot_key_action.xml
odoo/addons/iot_rule/views/iot_lock.xml
odoo/addons/iot_rule/views/iot_rule.xml
odoo/addons/iot_rule/views/res_partner.xml
odoo/addons/iot_rule/wizards/__init__.py
odoo/addons/iot_rule/wizards/iot_key_wizard.py
odoo/addons/iot_rule/wizards/iot_key_wizard.xml
odoo_addon_iot_rule-17.0.1.0.0.3.dist-info/METADATA
odoo_addon_iot_rule-17.0.1.0.0.3.dist-info/WHEEL
odoo_addon_iot_rule-17.0.1.0.0.3.dist-info/top_level.txt
odoo_addon_iot_rule-17.0.1.0.0.3.dist-info/RECORD
